PySafari2/PySafari.py
PySafari2/__init__.py
PySafari2-0.0.1.dist-info/LICENSE.txt
PySafari2-0.0.1.dist-info/METADATA
PySafari2-0.0.1.dist-info/WHEEL
PySafari2-0.0.1.dist-info/top_level.txt
PySafari2-0.0.1.dist-info/RECORD
