Metadata-Version: 2.1
Name: PySafari2
Version: 0.0.1
Summary: A small Safari like Python Web browser.
Home-page: https://github.com/pypa/PySafari
Author: Vihaan Pundir
Author-email: vihaan.pundir@ps517tccs.org
License: UNKNOWN
Platform: UNKNOWN
Classifier: Programming Language :: Python :: 3
Classifier: License :: OSI Approved :: MIT License
Classifier: Operating System :: OS Independent
Requires-Python: >=3.8
